{"data":{"query":{"docsData":{"modules":[{"clients":[{"remoteMethods":[{"accessor":"", "resourcePath":"", "isIsolated":true, "isRemote":true, "isResource":false, "isExtern":true, "parameters":[{"defaultValue":"", "type":{"orgName":"ballerina", "moduleName":"sql", "version":"1.11.0", "name":"ParameterizedQuery", "category":"libs", "isAnonymousUnionType":false, "isInclusion":false, "isArrayType":false, "isNullable":false, "isTuple":false, "isIntersectionType":false, "isParenthesisedType":false, "isTypeDesc":false, "isRestParam":false, "isDeprecated":false, "isPublic":false, "generateUserDefinedTypeLink":true, "memberTypes":[], "arrayDimensions":0}, "name":"sqlQuery", "description":"The SQL query such as `` `SELECT * from Album WHERE name=${albumName}` ``\n", "isDeprecated":false, "isReadOnly":false}, {"defaultValue":"<>", "annotationAttachments":[], "type":{"isAnonymousUnionType":false, "isInclusion":false, "isArrayType":false, "isNullable":false, "isTuple":false, "isIntersectionType":false, "isParenthesisedType":false, "isTypeDesc":true, "isRestParam":false, "isDeprecated":false, "isPublic":false, "generateUserDefinedTypeLink":true, "memberTypes":[], "arrayDimensions":0, "elementType":{"category":"inline_record", "isAnonymousUnionType":false, "isInclusion":false, "isArrayType":false, "isNullable":false, "isTuple":false, "isIntersectionType":false, "isParenthesisedType":false, "isTypeDesc":false, "isRestParam":false, "isDeprecated":false, "isPublic":false, "generateUserDefinedTypeLink":true, "memberTypes":[], "arrayDimensions":0}}, "name":"rowType", "description":"The `typedesc` of the record to which the result needs to be returned\n", "isDeprecated":false, "isReadOnly":false}], "returnParameters":[{"type":{"name":"stream", "category":"stream", "isAnonymousUnionType":false, "isInclusion":false, "isArrayType":false, "isNullable":false, "isTuple":false, "isIntersectionType":false, "isParenthesisedType":false, "isTypeDesc":false, "isRestParam":false, "isDeprecated":false, "isPublic":false, "generateUserDefinedTypeLink":true, "memberTypes":[{"orgName":"UNK_ORG", "moduleName":"UNK_MOD", "version":"UNK_VER", "name":"rowType", "category":"reference", "isAnonymousUnionType":false, "isInclusion":false, "isArrayType":false, "isNullable":false, "isTuple":false, "isIntersectionType":false, "isParenthesisedType":false, "isTypeDesc":false, "isRestParam":false, "isDeprecated":false, "isPublic":false, "generateUserDefinedTypeLink":true, "memberTypes":[], "arrayDimensions":0}, {"orgName":"ballerina", "moduleName":"sql", "version":"1.11.0", "name":"Error", "category":"libs", "isAnonymousUnionType":false, "isInclusion":false, "isArrayType":false, "isNullable":true, "isTuple":false, "isIntersectionType":false, "isParenthesisedType":false, "isTypeDesc":false, "isRestParam":false, "isDeprecated":false, "isPublic":false, "generateUserDefinedTypeLink":true, "memberTypes":[], "arrayDimensions":0}], "arrayDimensions":0}, "name":"", "description":"Stream of records in the `rowType` type\n", "isDeprecated":false, "isReadOnly":false}], "annotationAttachments":[], "name":"query", "description":"Executes the query, which may return multiple results.\nWhen processing the stream, make sure to consume all fetched data or close the stream.\n\n", "isDeprecated":false, "isReadOnly":false}, {"accessor":"", "resourcePath":"", "isIsolated":true, "isRemote":true, "isResource":false, "isExtern":true, "parameters":[{"defaultValue":"", "type":{"orgName":"ballerina", "moduleName":"sql", "version":"1.11.0", "name":"ParameterizedQuery", "category":"libs", "isAnonymousUnionType":false, "isInclusion":false, "isArrayType":false, "isNullable":false, "isTuple":false, "isIntersectionType":false, "isParenthesisedType":false, "isTypeDesc":false, "isRestParam":false, "isDeprecated":false, "isPublic":false, "generateUserDefinedTypeLink":true, "memberTypes":[], "arrayDimensions":0}, "name":"sqlQuery", "description":"The SQL query such as `` `SELECT * from Album WHERE name=${albumName}` ``\n", "isDeprecated":false, "isReadOnly":false}, {"defaultValue":"<>", "annotationAttachments":[], "type":{"isAnonymousUnionType":false, "isInclusion":false, "isArrayType":false, "isNullable":false, "isTuple":false, "isIntersectionType":false, "isParenthesisedType":false, "isTypeDesc":true, "isRestParam":false, "isDeprecated":false, "isPublic":false, "generateUserDefinedTypeLink":true, "memberTypes":[], "arrayDimensions":0, "elementType":{"name":"anydata", "category":"builtin", "isAnonymousUnionType":false, "isInclusion":false, "isArrayType":false, "isNullable":false, "isTuple":false, "isIntersectionType":false, "isParenthesisedType":false, "isTypeDesc":false, "isRestParam":false, "isDeprecated":false, "isPublic":false, "generateUserDefinedTypeLink":true, "memberTypes":[], "arrayDimensions":0}}, "name":"returnType", "description":"The `typedesc` of the record to which the result needs to be returned.\nIt can be a basic type if the query result contains only one column\n", "isDeprecated":false, "isReadOnly":false}], "returnParameters":[{"type":{"isAnonymousUnionType":true, "isInclusion":false, "isArrayType":false, "isNullable":false, "isTuple":false, "isIntersectionType":false, "isParenthesisedType":false, "isTypeDesc":false, "isRestParam":false, "isDeprecated":false, "isPublic":false, "generateUserDefinedTypeLink":true, "memberTypes":[{"name":"returnType", "category":"reference", "isAnonymousUnionType":false, "isInclusion":false, "isArrayType":false, "isNullable":false, "isTuple":false, "isIntersectionType":false, "isParenthesisedType":false, "isTypeDesc":false, "isRestParam":false, "isDeprecated":false, "isPublic":false, "generateUserDefinedTypeLink":false, "memberTypes":[], "arrayDimensions":0}, {"orgName":"ballerina", "moduleName":"sql", "version":"1.11.0", "name":"Error", "category":"libs", "isAnonymousUnionType":false, "isInclusion":false, "isArrayType":false, "isNullable":false, "isTuple":false, "isIntersectionType":false, "isParenthesisedType":false, "isTypeDesc":false, "isRestParam":false, "isDeprecated":false, "isPublic":false, "generateUserDefinedTypeLink":true, "memberTypes":[], "arrayDimensions":0}], "arrayDimensions":0}, "name":"", "description":"Result in the `returnType` type or an `sql:Error`\n", "isDeprecated":false, "isReadOnly":false}], "annotationAttachments":[], "name":"queryRow", "description":"Executes the query, which is expected to return at most one row of the result.\nIf the query does not return any results, an `sql:NoRowsError` is returned.\n\n", "isDeprecated":false, "isReadOnly":false}, {"accessor":"", "resourcePath":"", "isIsolated":true, "isRemote":true, "isResource":false, "isExtern":true, "parameters":[{"defaultValue":"", "type":{"orgName":"ballerina", "moduleName":"sql", "version":"1.11.0", "name":"ParameterizedQuery", "category":"libs", "isAnonymousUnionType":false, "isInclusion":false, "isArrayType":false, "isNullable":false, "isTuple":false, "isIntersectionType":false, "isParenthesisedType":false, "isTypeDesc":false, "isRestParam":false, "isDeprecated":false, "isPublic":false, "generateUserDefinedTypeLink":true, "memberTypes":[], "arrayDimensions":0}, "name":"sqlQuery", "description":"The SQL query such as `` `DELETE FROM Album WHERE artist=${artistName}` ``\n", "isDeprecated":false, "isReadOnly":false}], "returnParameters":[{"type":{"isAnonymousUnionType":true, "isInclusion":false, "isArrayType":false, "isNullable":false, "isTuple":false, "isIntersectionType":false, "isParenthesisedType":false, "isTypeDesc":false, "isRestParam":false, "isDeprecated":false, "isPublic":false, "generateUserDefinedTypeLink":true, "memberTypes":[{"orgName":"ballerina", "moduleName":"sql", "version":"1.11.0", "name":"ExecutionResult", "category":"libs", "isAnonymousUnionType":false, "isInclusion":false, "isArrayType":false, "isNullable":false, "isTuple":false, "isIntersectionType":false, "isParenthesisedType":false, "isTypeDesc":false, "isRestParam":false, "isDeprecated":false, "isPublic":false, "generateUserDefinedTypeLink":true, "memberTypes":[], "arrayDimensions":0}, {"orgName":"ballerina", "moduleName":"sql", "version":"1.11.0", "name":"Error", "category":"libs", "isAnonymousUnionType":false, "isInclusion":false, "isArrayType":false, "isNullable":false, "isTuple":false, "isIntersectionType":false, "isParenthesisedType":false, "isTypeDesc":false, "isRestParam":false, "isDeprecated":false, "isPublic":false, "generateUserDefinedTypeLink":true, "memberTypes":[], "arrayDimensions":0}], "arrayDimensions":0}, "name":"", "description":"Metadata of the query execution as an `sql:ExecutionResult` or an `sql:Error`\n", "isDeprecated":false, "isReadOnly":false}], "annotationAttachments":[], "name":"execute", "description":"Executes the SQL query. Only the metadata of the execution is returned (not the results from the query).\n\n", "isDeprecated":false, "isReadOnly":false}, {"accessor":"", "resourcePath":"", "isIsolated":true, "isRemote":true, "isResource":false, "isExtern":false, "parameters":[{"defaultValue":"", "type":{"isAnonymousUnionType":false, "isInclusion":false, "isArrayType":true, "isNullable":false, "isTuple":false, "isIntersectionType":false, "isParenthesisedType":false, "isTypeDesc":false, "isRestParam":false, "isDeprecated":false, "isPublic":false, "generateUserDefinedTypeLink":true, "memberTypes":[], "arrayDimensions":1, "elementType":{"orgName":"ballerina", "moduleName":"sql", "version":"1.11.0", "name":"ParameterizedQuery", "category":"libs", "isAnonymousUnionType":false, "isInclusion":false, "isArrayType":false, "isNullable":false, "isTuple":false, "isIntersectionType":false, "isParenthesisedType":false, "isTypeDesc":false, "isRestParam":false, "isDeprecated":false, "isPublic":false, "generateUserDefinedTypeLink":true, "memberTypes":[], "arrayDimensions":0}}, "name":"sqlQueries", "description":"The SQL query with multiple sets of parameters\n", "isDeprecated":false, "isReadOnly":false}], "returnParameters":[{"type":{"isAnonymousUnionType":true, "isInclusion":false, "isArrayType":false, "isNullable":false, "isTuple":false, "isIntersectionType":false, "isParenthesisedType":false, "isTypeDesc":false, "isRestParam":false, "isDeprecated":false, "isPublic":false, "generateUserDefinedTypeLink":true, "memberTypes":[{"isAnonymousUnionType":false, "isInclusion":false, "isArrayType":true, "isNullable":false, "isTuple":false, "isIntersectionType":false, "isParenthesisedType":false, "isTypeDesc":false, "isRestParam":false, "isDeprecated":false, "isPublic":false, "generateUserDefinedTypeLink":true, "memberTypes":[], "arrayDimensions":1, "elementType":{"orgName":"ballerina", "moduleName":"sql", "version":"1.11.0", "name":"ExecutionResult", "category":"libs", "isAnonymousUnionType":false, "isInclusion":false, "isArrayType":false, "isNullable":false, "isTuple":false, "isIntersectionType":false, "isParenthesisedType":false, "isTypeDesc":false, "isRestParam":false, "isDeprecated":false, "isPublic":false, "generateUserDefinedTypeLink":true, "memberTypes":[], "arrayDimensions":0}}, {"orgName":"ballerina", "moduleName":"sql", "version":"1.11.0", "name":"Error", "category":"libs", "isAnonymousUnionType":false, "isInclusion":false, "isArrayType":false, "isNullable":false, "isTuple":false, "isIntersectionType":false, "isParenthesisedType":false, "isTypeDesc":false, "isRestParam":false, "isDeprecated":false, "isPublic":false, "generateUserDefinedTypeLink":true, "memberTypes":[], "arrayDimensions":0}], "arrayDimensions":0}, "name":"", "description":"Metadata of the query execution as an `sql:ExecutionResult[]` or an `sql:Error`\n", "isDeprecated":false, "isReadOnly":false}], "annotationAttachments":[], "name":"batchExecute", "description":"Executes the SQL query with multiple sets of parameters in a batch. Only the metadata of the execution is returned (not results from the query).\nIf one of the commands in the batch fails, the `sql:BatchExecuteError` will be returned immediately.\n\n", "isDeprecated":false, "isReadOnly":false}, {"accessor":"", "resourcePath":"", "isIsolated":true, "isRemote":true, "isResource":false, "isExtern":true, "parameters":[{"defaultValue":"", "type":{"orgName":"ballerina", "moduleName":"sql", "version":"1.11.0", "name":"ParameterizedCallQuery", "category":"libs", "isAnonymousUnionType":false, "isInclusion":false, "isArrayType":false, "isNullable":false, "isTuple":false, "isIntersectionType":false, "isParenthesisedType":false, "isTypeDesc":false, "isRestParam":false, "isDeprecated":false, "isPublic":false, "generateUserDefinedTypeLink":true, "memberTypes":[], "arrayDimensions":0}, "name":"sqlQuery", "description":"The SQL query such as `` `CALL sp_GetAlbums();` ``\n", "isDeprecated":false, "isReadOnly":false}, {"defaultValue":"[]", "annotationAttachments":[], "type":{"isAnonymousUnionType":false, "isInclusion":false, "isArrayType":true, "isNullable":false, "isTuple":false, "isIntersectionType":false, "isParenthesisedType":false, "isTypeDesc":false, "isRestParam":false, "isDeprecated":false, "isPublic":false, "generateUserDefinedTypeLink":true, "memberTypes":[], "arrayDimensions":1, "elementType":{"isAnonymousUnionType":false, "isInclusion":false, "isArrayType":false, "isNullable":false, "isTuple":false, "isIntersectionType":false, "isParenthesisedType":false, "isTypeDesc":true, "isRestParam":false, "isDeprecated":false, "isPublic":false, "generateUserDefinedTypeLink":true, "memberTypes":[], "arrayDimensions":0, "elementType":{"category":"inline_record", "isAnonymousUnionType":false, "isInclusion":false, "isArrayType":false, "isNullable":false, "isTuple":false, "isIntersectionType":false, "isParenthesisedType":false, "isTypeDesc":false, "isRestParam":false, "isDeprecated":false, "isPublic":false, "generateUserDefinedTypeLink":true, "memberTypes":[], "arrayDimensions":0}}}, "name":"rowTypes", "description":"`typedesc` array of the records to which the results need to be returned\n", "isDeprecated":false, "isReadOnly":false}], "returnParameters":[{"type":{"isAnonymousUnionType":true, "isInclusion":false, "isArrayType":false, "isNullable":false, "isTuple":false, "isIntersectionType":false, "isParenthesisedType":false, "isTypeDesc":false, "isRestParam":false, "isDeprecated":false, "isPublic":false, "generateUserDefinedTypeLink":true, "memberTypes":[{"orgName":"ballerina", "moduleName":"sql", "version":"1.11.0", "name":"ProcedureCallResult", "category":"libs", "isAnonymousUnionType":false, "isInclusion":false, "isArrayType":false, "isNullable":false, "isTuple":false, "isIntersectionType":false, "isParenthesisedType":false, "isTypeDesc":false, "isRestParam":false, "isDeprecated":false, "isPublic":false, "generateUserDefinedTypeLink":true, "memberTypes":[], "arrayDimensions":0}, {"orgName":"ballerina", "moduleName":"sql", "version":"1.11.0", "name":"Error", "category":"libs", "isAnonymousUnionType":false, "isInclusion":false, "isArrayType":false, "isNullable":false, "isTuple":false, "isIntersectionType":false, "isParenthesisedType":false, "isTypeDesc":false, "isRestParam":false, "isDeprecated":false, "isPublic":false, "generateUserDefinedTypeLink":true, "memberTypes":[], "arrayDimensions":0}], "arrayDimensions":0}, "name":"", "description":"Summary of the execution and results are returned in an `sql:ProcedureCallResult`, or an `sql:Error`\n", "isDeprecated":false, "isReadOnly":false}], "annotationAttachments":[], "name":"call", "description":"Executes an SQL query, which calls a stored procedure. This may or may not\nreturn results. Once the results are processed, the `close` method on `sql:ProcedureCallResult` must be called.\n\n", "isDeprecated":false, "isReadOnly":false}], "resourceMethods":[], "fields":[], "methods":[{"accessor":"", "resourcePath":"", "isIsolated":true, "isRemote":false, "isResource":false, "isExtern":false, "parameters":[{"defaultValue":"\"localhost\"", "annotationAttachments":[], "type":{"name":"string", "category":"builtin", "isAnonymousUnionType":false, "isInclusion":false, "isArrayType":false, "isNullable":false, "isTuple":false, "isIntersectionType":false, "isParenthesisedType":false, "isTypeDesc":false, "isRestParam":false, "isDeprecated":false, "isPublic":false, "generateUserDefinedTypeLink":true, "memberTypes":[], "arrayDimensions":0}, "name":"host", "description":"Hostname of the Oracle database server\n", "isDeprecated":false, "isReadOnly":false}, {"defaultValue":"\"sys\"", "annotationAttachments":[], "type":{"name":"string", "category":"builtin", "isAnonymousUnionType":false, "isInclusion":false, "isArrayType":false, "isNullable":true, "isTuple":false, "isIntersectionType":false, "isParenthesisedType":false, "isTypeDesc":false, "isRestParam":false, "isDeprecated":false, "isPublic":false, "generateUserDefinedTypeLink":true, "memberTypes":[], "arrayDimensions":0}, "name":"user", "description":"Name of a user of the Oracle database server\n", "isDeprecated":false, "isReadOnly":false}, {"defaultValue":"()", "annotationAttachments":[], "type":{"name":"string", "category":"builtin", "isAnonymousUnionType":false, "isInclusion":false, "isArrayType":false, "isNullable":true, "isTuple":false, "isIntersectionType":false, "isParenthesisedType":false, "isTypeDesc":false, "isRestParam":false, "isDeprecated":false, "isPublic":false, "generateUserDefinedTypeLink":true, "memberTypes":[], "arrayDimensions":0}, "name":"password", "description":"The password of the Oracle database server for the provided username\n", "isDeprecated":false, "isReadOnly":false}, {"defaultValue":"()", "annotationAttachments":[], "type":{"name":"string", "category":"builtin", "isAnonymousUnionType":false, "isInclusion":false, "isArrayType":false, "isNullable":true, "isTuple":false, "isIntersectionType":false, "isParenthesisedType":false, "isTypeDesc":false, "isRestParam":false, "isDeprecated":false, "isPublic":false, "generateUserDefinedTypeLink":true, "memberTypes":[], "arrayDimensions":0}, "name":"database", "description":"System identifier or the service name of the database\n", "isDeprecated":false, "isReadOnly":false}, {"defaultValue":"1521", "annotationAttachments":[], "type":{"name":"int", "category":"builtin", "isAnonymousUnionType":false, "isInclusion":false, "isArrayType":false, "isNullable":false, "isTuple":false, "isIntersectionType":false, "isParenthesisedType":false, "isTypeDesc":false, "isRestParam":false, "isDeprecated":false, "isPublic":false, "generateUserDefinedTypeLink":true, "memberTypes":[], "arrayDimensions":0}, "name":"port", "description":"Port number of the Oracle database server\n", "isDeprecated":false, "isReadOnly":false}, {"defaultValue":"()", "annotationAttachments":[], "type":{"orgName":"ballerinax", "moduleName":"oracledb", "version":"1.11.0", "name":"Options", "category":"records", "isAnonymousUnionType":false, "isInclusion":false, "isArrayType":false, "isNullable":true, "isTuple":false, "isIntersectionType":false, "isParenthesisedType":false, "isTypeDesc":false, "isRestParam":false, "isDeprecated":false, "isPublic":false, "generateUserDefinedTypeLink":true, "memberTypes":[], "arrayDimensions":0}, "name":"options", "description":"Oracle database connection properties\n", "isDeprecated":false, "isReadOnly":false}, {"defaultValue":"()", "annotationAttachments":[], "type":{"orgName":"ballerina", "moduleName":"sql", "version":"1.11.0", "name":"ConnectionPool", "category":"libs", "isAnonymousUnionType":false, "isInclusion":false, "isArrayType":false, "isNullable":true, "isTuple":false, "isIntersectionType":false, "isParenthesisedType":false, "isTypeDesc":false, "isRestParam":false, "isDeprecated":false, "isPublic":false, "generateUserDefinedTypeLink":true, "memberTypes":[], "arrayDimensions":0}, "name":"connectionPool", "description":"The `sql:ConnectionPool` object to be used within the client. If there is no\n`connectionPool` provided, the global connection pool will be used\n", "isDeprecated":false, "isReadOnly":false}], "returnParameters":[{"type":{"orgName":"ballerina", "moduleName":"sql", "version":"1.11.0", "name":"Error", "category":"libs", "isAnonymousUnionType":false, "isInclusion":false, "isArrayType":false, "isNullable":true, "isTuple":false, "isIntersectionType":false, "isParenthesisedType":false, "isTypeDesc":false, "isRestParam":false, "isDeprecated":false, "isPublic":false, "generateUserDefinedTypeLink":true, "memberTypes":[], "arrayDimensions":0}, "name":"", "description":"An `sql:Error` if the client creation fails\n", "isDeprecated":false, "isReadOnly":false}], "annotationAttachments":[], "name":"init", "description":"Initializes the OracleDB Client. The client must be kept open throughout the application lifetime.\n\n", "isDeprecated":false, "isReadOnly":false}, {"accessor":"", "resourcePath":"", "isIsolated":true, "isRemote":true, "isResource":false, "isExtern":true, "parameters":[{"defaultValue":"", "type":{"orgName":"ballerina", "moduleName":"sql", "version":"1.11.0", "name":"ParameterizedQuery", "category":"libs", "isAnonymousUnionType":false, "isInclusion":false, "isArrayType":false, "isNullable":false, "isTuple":false, "isIntersectionType":false, "isParenthesisedType":false, "isTypeDesc":false, "isRestParam":false, "isDeprecated":false, "isPublic":false, "generateUserDefinedTypeLink":true, "memberTypes":[], "arrayDimensions":0}, "name":"sqlQuery", "description":"The SQL query such as `` `SELECT * from Album WHERE name=${albumName}` ``\n", "isDeprecated":false, "isReadOnly":false}, {"defaultValue":"<>", "annotationAttachments":[], "type":{"isAnonymousUnionType":false, "isInclusion":false, "isArrayType":false, "isNullable":false, "isTuple":false, "isIntersectionType":false, "isParenthesisedType":false, "isTypeDesc":true, "isRestParam":false, "isDeprecated":false, "isPublic":false, "generateUserDefinedTypeLink":true, "memberTypes":[], "arrayDimensions":0, "elementType":{"category":"inline_record", "isAnonymousUnionType":false, "isInclusion":false, "isArrayType":false, "isNullable":false, "isTuple":false, "isIntersectionType":false, "isParenthesisedType":false, "isTypeDesc":false, "isRestParam":false, "isDeprecated":false, "isPublic":false, "generateUserDefinedTypeLink":true, "memberTypes":[], "arrayDimensions":0}}, "name":"rowType", "description":"The `typedesc` of the record to which the result needs to be returned\n", "isDeprecated":false, "isReadOnly":false}], "returnParameters":[{"type":{"name":"stream", "category":"stream", "isAnonymousUnionType":false, "isInclusion":false, "isArrayType":false, "isNullable":false, "isTuple":false, "isIntersectionType":false, "isParenthesisedType":false, "isTypeDesc":false, "isRestParam":false, "isDeprecated":false, "isPublic":false, "generateUserDefinedTypeLink":true, "memberTypes":[{"orgName":"UNK_ORG", "moduleName":"UNK_MOD", "version":"UNK_VER", "name":"rowType", "category":"reference", "isAnonymousUnionType":false, "isInclusion":false, "isArrayType":false, "isNullable":false, "isTuple":false, "isIntersectionType":false, "isParenthesisedType":false, "isTypeDesc":false, "isRestParam":false, "isDeprecated":false, "isPublic":false, "generateUserDefinedTypeLink":true, "memberTypes":[], "arrayDimensions":0}, {"orgName":"ballerina", "moduleName":"sql", "version":"1.11.0", "name":"Error", "category":"libs", "isAnonymousUnionType":false, "isInclusion":false, "isArrayType":false, "isNullable":true, "isTuple":false, "isIntersectionType":false, "isParenthesisedType":false, "isTypeDesc":false, "isRestParam":false, "isDeprecated":false, "isPublic":false, "generateUserDefinedTypeLink":true, "memberTypes":[], "arrayDimensions":0}], "arrayDimensions":0}, "name":"", "description":"Stream of records in the `rowType` type\n", "isDeprecated":false, "isReadOnly":false}], "annotationAttachments":[], "name":"query", "description":"Executes the query, which may return multiple results.\nWhen processing the stream, make sure to consume all fetched data or close the stream.\n\n", "isDeprecated":false, "isReadOnly":false}, {"accessor":"", "resourcePath":"", "isIsolated":true, "isRemote":true, "isResource":false, "isExtern":true, "parameters":[{"defaultValue":"", "type":{"orgName":"ballerina", "moduleName":"sql", "version":"1.11.0", "name":"ParameterizedQuery", "category":"libs", "isAnonymousUnionType":false, "isInclusion":false, "isArrayType":false, "isNullable":false, "isTuple":false, "isIntersectionType":false, "isParenthesisedType":false, "isTypeDesc":false, "isRestParam":false, "isDeprecated":false, "isPublic":false, "generateUserDefinedTypeLink":true, "memberTypes":[], "arrayDimensions":0}, "name":"sqlQuery", "description":"The SQL query such as `` `SELECT * from Album WHERE name=${albumName}` ``\n", "isDeprecated":false, "isReadOnly":false}, {"defaultValue":"<>", "annotationAttachments":[], "type":{"isAnonymousUnionType":false, "isInclusion":false, "isArrayType":false, "isNullable":false, "isTuple":false, "isIntersectionType":false, "isParenthesisedType":false, "isTypeDesc":true, "isRestParam":false, "isDeprecated":false, "isPublic":false, "generateUserDefinedTypeLink":true, "memberTypes":[], "arrayDimensions":0, "elementType":{"name":"anydata", "category":"builtin", "isAnonymousUnionType":false, "isInclusion":false, "isArrayType":false, "isNullable":false, "isTuple":false, "isIntersectionType":false, "isParenthesisedType":false, "isTypeDesc":false, "isRestParam":false, "isDeprecated":false, "isPublic":false, "generateUserDefinedTypeLink":true, "memberTypes":[], "arrayDimensions":0}}, "name":"returnType", "description":"The `typedesc` of the record to which the result needs to be returned.\nIt can be a basic type if the query result contains only one column\n", "isDeprecated":false, "isReadOnly":false}], "returnParameters":[{"type":{"isAnonymousUnionType":true, "isInclusion":false, "isArrayType":false, "isNullable":false, "isTuple":false, "isIntersectionType":false, "isParenthesisedType":false, "isTypeDesc":false, "isRestParam":false, "isDeprecated":false, "isPublic":false, "generateUserDefinedTypeLink":true, "memberTypes":[{"name":"returnType", "category":"reference", "isAnonymousUnionType":false, "isInclusion":false, "isArrayType":false, "isNullable":false, "isTuple":false, "isIntersectionType":false, "isParenthesisedType":false, "isTypeDesc":false, "isRestParam":false, "isDeprecated":false, "isPublic":false, "generateUserDefinedTypeLink":false, "memberTypes":[], "arrayDimensions":0}, {"orgName":"ballerina", "moduleName":"sql", "version":"1.11.0", "name":"Error", "category":"libs", "isAnonymousUnionType":false, "isInclusion":false, "isArrayType":false, "isNullable":false, "isTuple":false, "isIntersectionType":false, "isParenthesisedType":false, "isTypeDesc":false, "isRestParam":false, "isDeprecated":false, "isPublic":false, "generateUserDefinedTypeLink":true, "memberTypes":[], "arrayDimensions":0}], "arrayDimensions":0}, "name":"", "description":"Result in the `returnType` type or an `sql:Error`\n", "isDeprecated":false, "isReadOnly":false}], "annotationAttachments":[], "name":"queryRow", "description":"Executes the query, which is expected to return at most one row of the result.\nIf the query does not return any results, an `sql:NoRowsError` is returned.\n\n", "isDeprecated":false, "isReadOnly":false}, {"accessor":"", "resourcePath":"", "isIsolated":true, "isRemote":true, "isResource":false, "isExtern":true, "parameters":[{"defaultValue":"", "type":{"orgName":"ballerina", "moduleName":"sql", "version":"1.11.0", "name":"ParameterizedQuery", "category":"libs", "isAnonymousUnionType":false, "isInclusion":false, "isArrayType":false, "isNullable":false, "isTuple":false, "isIntersectionType":false, "isParenthesisedType":false, "isTypeDesc":false, "isRestParam":false, "isDeprecated":false, "isPublic":false, "generateUserDefinedTypeLink":true, "memberTypes":[], "arrayDimensions":0}, "name":"sqlQuery", "description":"The SQL query such as `` `DELETE FROM Album WHERE artist=${artistName}` ``\n", "isDeprecated":false, "isReadOnly":false}], "returnParameters":[{"type":{"isAnonymousUnionType":true, "isInclusion":false, "isArrayType":false, "isNullable":false, "isTuple":false, "isIntersectionType":false, "isParenthesisedType":false, "isTypeDesc":false, "isRestParam":false, "isDeprecated":false, "isPublic":false, "generateUserDefinedTypeLink":true, "memberTypes":[{"orgName":"ballerina", "moduleName":"sql", "version":"1.11.0", "name":"ExecutionResult", "category":"libs", "isAnonymousUnionType":false, "isInclusion":false, "isArrayType":false, "isNullable":false, "isTuple":false, "isIntersectionType":false, "isParenthesisedType":false, "isTypeDesc":false, "isRestParam":false, "isDeprecated":false, "isPublic":false, "generateUserDefinedTypeLink":true, "memberTypes":[], "arrayDimensions":0}, {"orgName":"ballerina", "moduleName":"sql", "version":"1.11.0", "name":"Error", "category":"libs", "isAnonymousUnionType":false, "isInclusion":false, "isArrayType":false, "isNullable":false, "isTuple":false, "isIntersectionType":false, "isParenthesisedType":false, "isTypeDesc":false, "isRestParam":false, "isDeprecated":false, "isPublic":false, "generateUserDefinedTypeLink":true, "memberTypes":[], "arrayDimensions":0}], "arrayDimensions":0}, "name":"", "description":"Metadata of the query execution as an `sql:ExecutionResult` or an `sql:Error`\n", "isDeprecated":false, "isReadOnly":false}], "annotationAttachments":[], "name":"execute", "description":"Executes the SQL query. Only the metadata of the execution is returned (not the results from the query).\n\n", "isDeprecated":false, "isReadOnly":false}, {"accessor":"", "resourcePath":"", "isIsolated":true, "isRemote":true, "isResource":false, "isExtern":false, "parameters":[{"defaultValue":"", "type":{"isAnonymousUnionType":false, "isInclusion":false, "isArrayType":true, "isNullable":false, "isTuple":false, "isIntersectionType":false, "isParenthesisedType":false, "isTypeDesc":false, "isRestParam":false, "isDeprecated":false, "isPublic":false, "generateUserDefinedTypeLink":true, "memberTypes":[], "arrayDimensions":1, "elementType":{"orgName":"ballerina", "moduleName":"sql", "version":"1.11.0", "name":"ParameterizedQuery", "category":"libs", "isAnonymousUnionType":false, "isInclusion":false, "isArrayType":false, "isNullable":false, "isTuple":false, "isIntersectionType":false, "isParenthesisedType":false, "isTypeDesc":false, "isRestParam":false, "isDeprecated":false, "isPublic":false, "generateUserDefinedTypeLink":true, "memberTypes":[], "arrayDimensions":0}}, "name":"sqlQueries", "description":"The SQL query with multiple sets of parameters\n", "isDeprecated":false, "isReadOnly":false}], "returnParameters":[{"type":{"isAnonymousUnionType":true, "isInclusion":false, "isArrayType":false, "isNullable":false, "isTuple":false, "isIntersectionType":false, "isParenthesisedType":false, "isTypeDesc":false, "isRestParam":false, "isDeprecated":false, "isPublic":false, "generateUserDefinedTypeLink":true, "memberTypes":[{"isAnonymousUnionType":false, "isInclusion":false, "isArrayType":true, "isNullable":false, "isTuple":false, "isIntersectionType":false, "isParenthesisedType":false, "isTypeDesc":false, "isRestParam":false, "isDeprecated":false, "isPublic":false, "generateUserDefinedTypeLink":true, "memberTypes":[], "arrayDimensions":1, "elementType":{"orgName":"ballerina", "moduleName":"sql", "version":"1.11.0", "name":"ExecutionResult", "category":"libs", "isAnonymousUnionType":false, "isInclusion":false, "isArrayType":false, "isNullable":false, "isTuple":false, "isIntersectionType":false, "isParenthesisedType":false, "isTypeDesc":false, "isRestParam":false, "isDeprecated":false, "isPublic":false, "generateUserDefinedTypeLink":true, "memberTypes":[], "arrayDimensions":0}}, {"orgName":"ballerina", "moduleName":"sql", "version":"1.11.0", "name":"Error", "category":"libs", "isAnonymousUnionType":false, "isInclusion":false, "isArrayType":false, "isNullable":false, "isTuple":false, "isIntersectionType":false, "isParenthesisedType":false, "isTypeDesc":false, "isRestParam":false, "isDeprecated":false, "isPublic":false, "generateUserDefinedTypeLink":true, "memberTypes":[], "arrayDimensions":0}], "arrayDimensions":0}, "name":"", "description":"Metadata of the query execution as an `sql:ExecutionResult[]` or an `sql:Error`\n", "isDeprecated":false, "isReadOnly":false}], "annotationAttachments":[], "name":"batchExecute", "description":"Executes the SQL query with multiple sets of parameters in a batch. Only the metadata of the execution is returned (not results from the query).\nIf one of the commands in the batch fails, the `sql:BatchExecuteError` will be returned immediately.\n\n", "isDeprecated":false, "isReadOnly":false}, {"accessor":"", "resourcePath":"", "isIsolated":true, "isRemote":true, "isResource":false, "isExtern":true, "parameters":[{"defaultValue":"", "type":{"orgName":"ballerina", "moduleName":"sql", "version":"1.11.0", "name":"ParameterizedCallQuery", "category":"libs", "isAnonymousUnionType":false, "isInclusion":false, "isArrayType":false, "isNullable":false, "isTuple":false, "isIntersectionType":false, "isParenthesisedType":false, "isTypeDesc":false, "isRestParam":false, "isDeprecated":false, "isPublic":false, "generateUserDefinedTypeLink":true, "memberTypes":[], "arrayDimensions":0}, "name":"sqlQuery", "description":"The SQL query such as `` `CALL sp_GetAlbums();` ``\n", "isDeprecated":false, "isReadOnly":false}, {"defaultValue":"[]", "annotationAttachments":[], "type":{"isAnonymousUnionType":false, "isInclusion":false, "isArrayType":true, "isNullable":false, "isTuple":false, "isIntersectionType":false, "isParenthesisedType":false, "isTypeDesc":false, "isRestParam":false, "isDeprecated":false, "isPublic":false, "generateUserDefinedTypeLink":true, "memberTypes":[], "arrayDimensions":1, "elementType":{"isAnonymousUnionType":false, "isInclusion":false, "isArrayType":false, "isNullable":false, "isTuple":false, "isIntersectionType":false, "isParenthesisedType":false, "isTypeDesc":true, "isRestParam":false, "isDeprecated":false, "isPublic":false, "generateUserDefinedTypeLink":true, "memberTypes":[], "arrayDimensions":0, "elementType":{"category":"inline_record", "isAnonymousUnionType":false, "isInclusion":false, "isArrayType":false, "isNullable":false, "isTuple":false, "isIntersectionType":false, "isParenthesisedType":false, "isTypeDesc":false, "isRestParam":false, "isDeprecated":false, "isPublic":false, "generateUserDefinedTypeLink":true, "memberTypes":[], "arrayDimensions":0}}}, "name":"rowTypes", "description":"`typedesc` array of the records to which the results need to be returned\n", "isDeprecated":false, "isReadOnly":false}], "returnParameters":[{"type":{"isAnonymousUnionType":true, "isInclusion":false, "isArrayType":false, "isNullable":false, "isTuple":false, "isIntersectionType":false, "isParenthesisedType":false, "isTypeDesc":false, "isRestParam":false, "isDeprecated":false, "isPublic":false, "generateUserDefinedTypeLink":true, "memberTypes":[{"orgName":"ballerina", "moduleName":"sql", "version":"1.11.0", "name":"ProcedureCallResult", "category":"libs", "isAnonymousUnionType":false, "isInclusion":false, "isArrayType":false, "isNullable":false, "isTuple":false, "isIntersectionType":false, "isParenthesisedType":false, "isTypeDesc":false, "isRestParam":false, "isDeprecated":false, "isPublic":false, "generateUserDefinedTypeLink":true, "memberTypes":[], "arrayDimensions":0}, {"orgName":"ballerina", "moduleName":"sql", "version":"1.11.0", "name":"Error", "category":"libs", "isAnonymousUnionType":false, "isInclusion":false, "isArrayType":false, "isNullable":false, "isTuple":false, "isIntersectionType":false, "isParenthesisedType":false, "isTypeDesc":false, "isRestParam":false, "isDeprecated":false, "isPublic":false, "generateUserDefinedTypeLink":true, "memberTypes":[], "arrayDimensions":0}], "arrayDimensions":0}, "name":"", "description":"Summary of the execution and results are returned in an `sql:ProcedureCallResult`, or an `sql:Error`\n", "isDeprecated":false, "isReadOnly":false}], "annotationAttachments":[], "name":"call", "description":"Executes an SQL query, which calls a stored procedure. This may or may not\nreturn results. Once the results are processed, the `close` method on `sql:ProcedureCallResult` must be called.\n\n", "isDeprecated":false, "isReadOnly":false}, {"accessor":"", "resourcePath":"", "isIsolated":true, "isRemote":false, "isResource":false, "isExtern":true, "parameters":[], "returnParameters":[{"type":{"orgName":"ballerina", "moduleName":"sql", "version":"1.11.0", "name":"Error", "category":"libs", "isAnonymousUnionType":false, "isInclusion":false, "isArrayType":false, "isNullable":true, "isTuple":false, "isIntersectionType":false, "isParenthesisedType":false, "isTypeDesc":false, "isRestParam":false, "isDeprecated":false, "isPublic":false, "generateUserDefinedTypeLink":true, "memberTypes":[], "arrayDimensions":0}, "name":"", "description":"`()` or an `sql:Error`\n", "isDeprecated":false, "isReadOnly":false}], "annotationAttachments":[], "name":"close", "description":"Closes the JDBC client and shuts down the connection pool. The client must be closed only at the end of the\napplication lifetime (or closed for graceful stops in a service).\n\n", "isDeprecated":false, "isReadOnly":false}], "initMethod":{"accessor":"", "resourcePath":"", "isIsolated":true, "isRemote":false, "isResource":false, "isExtern":false, "parameters":[{"defaultValue":"\"localhost\"", "annotationAttachments":[], "type":{"name":"string", "category":"builtin", "isAnonymousUnionType":false, "isInclusion":false, "isArrayType":false, "isNullable":false, "isTuple":false, "isIntersectionType":false, "isParenthesisedType":false, "isTypeDesc":false, "isRestParam":false, "isDeprecated":false, "isPublic":false, "generateUserDefinedTypeLink":true, "memberTypes":[], "arrayDimensions":0}, "name":"host", "description":"Hostname of the Oracle database server\n", "isDeprecated":false, "isReadOnly":false}, {"defaultValue":"\"sys\"", "annotationAttachments":[], "type":{"name":"string", "category":"builtin", "isAnonymousUnionType":false, "isInclusion":false, "isArrayType":false, "isNullable":true, "isTuple":false, "isIntersectionType":false, "isParenthesisedType":false, "isTypeDesc":false, "isRestParam":false, "isDeprecated":false, "isPublic":false, "generateUserDefinedTypeLink":true, "memberTypes":[], "arrayDimensions":0}, "name":"user", "description":"Name of a user of the Oracle database server\n", "isDeprecated":false, "isReadOnly":false}, {"defaultValue":"()", "annotationAttachments":[], "type":{"name":"string", "category":"builtin", "isAnonymousUnionType":false, "isInclusion":false, "isArrayType":false, "isNullable":true, "isTuple":false, "isIntersectionType":false, "isParenthesisedType":false, "isTypeDesc":false, "isRestParam":false, "isDeprecated":false, "isPublic":false, "generateUserDefinedTypeLink":true, "memberTypes":[], "arrayDimensions":0}, "name":"password", "description":"The password of the Oracle database server for the provided username\n", "isDeprecated":false, "isReadOnly":false}, {"defaultValue":"()", "annotationAttachments":[], "type":{"name":"string", "category":"builtin", "isAnonymousUnionType":false, "isInclusion":false, "isArrayType":false, "isNullable":true, "isTuple":false, "isIntersectionType":false, "isParenthesisedType":false, "isTypeDesc":false, "isRestParam":false, "isDeprecated":false, "isPublic":false, "generateUserDefinedTypeLink":true, "memberTypes":[], "arrayDimensions":0}, "name":"database", "description":"System identifier or the service name of the database\n", "isDeprecated":false, "isReadOnly":false}, {"defaultValue":"1521", "annotationAttachments":[], "type":{"name":"int", "category":"builtin", "isAnonymousUnionType":false, "isInclusion":false, "isArrayType":false, "isNullable":false, "isTuple":false, "isIntersectionType":false, "isParenthesisedType":false, "isTypeDesc":false, "isRestParam":false, "isDeprecated":false, "isPublic":false, "generateUserDefinedTypeLink":true, "memberTypes":[], "arrayDimensions":0}, "name":"port", "description":"Port number of the Oracle database server\n", "isDeprecated":false, "isReadOnly":false}, {"defaultValue":"()", "annotationAttachments":[], "type":{"orgName":"ballerinax", "moduleName":"oracledb", "version":"1.11.0", "name":"Options", "category":"records", "isAnonymousUnionType":false, "isInclusion":false, "isArrayType":false, "isNullable":true, "isTuple":false, "isIntersectionType":false, "isParenthesisedType":false, "isTypeDesc":false, "isRestParam":false, "isDeprecated":false, "isPublic":false, "generateUserDefinedTypeLink":true, "memberTypes":[], "arrayDimensions":0}, "name":"options", "description":"Oracle database connection properties\n", "isDeprecated":false, "isReadOnly":false}, {"defaultValue":"()", "annotationAttachments":[], "type":{"orgName":"ballerina", "moduleName":"sql", "version":"1.11.0", "name":"ConnectionPool", "category":"libs", "isAnonymousUnionType":false, "isInclusion":false, "isArrayType":false, "isNullable":true, "isTuple":false, "isIntersectionType":false, "isParenthesisedType":false, "isTypeDesc":false, "isRestParam":false, "isDeprecated":false, "isPublic":false, "generateUserDefinedTypeLink":true, "memberTypes":[], "arrayDimensions":0}, "name":"connectionPool", "description":"The `sql:ConnectionPool` object to be used within the client. If there is no\n`connectionPool` provided, the global connection pool will be used\n", "isDeprecated":false, "isReadOnly":false}], "returnParameters":[{"type":{"orgName":"ballerina", "moduleName":"sql", "version":"1.11.0", "name":"Error", "category":"libs", "isAnonymousUnionType":false, "isInclusion":false, "isArrayType":false, "isNullable":true, "isTuple":false, "isIntersectionType":false, "isParenthesisedType":false, "isTypeDesc":false, "isRestParam":false, "isDeprecated":false, "isPublic":false, "generateUserDefinedTypeLink":true, "memberTypes":[], "arrayDimensions":0}, "name":"", "description":"An `sql:Error` if the client creation fails\n", "isDeprecated":false, "isReadOnly":false}], "annotationAttachments":[], "name":"init", "description":"Initializes the OracleDB Client. The client must be kept open throughout the application lifetime.\n\n", "isDeprecated":false, "isReadOnly":false}, "otherMethods":[{"accessor":"", "resourcePath":"", "isIsolated":true, "isRemote":false, "isResource":false, "isExtern":true, "parameters":[], "returnParameters":[{"type":{"orgName":"ballerina", "moduleName":"sql", "version":"1.11.0", "name":"Error", "category":"libs", "isAnonymousUnionType":false, "isInclusion":false, "isArrayType":false, "isNullable":true, "isTuple":false, "isIntersectionType":false, "isParenthesisedType":false, "isTypeDesc":false, "isRestParam":false, "isDeprecated":false, "isPublic":false, "generateUserDefinedTypeLink":true, "memberTypes":[], "arrayDimensions":0}, "name":"", "description":"`()` or an `sql:Error`\n", "isDeprecated":false, "isReadOnly":false}], "annotationAttachments":[], "name":"close", "description":"Closes the JDBC client and shuts down the connection pool. The client must be closed only at the end of the\napplication lifetime (or closed for graceful stops in a service).\n\n", "isDeprecated":false, "isReadOnly":false}], "isIsolated":true, "isService":false, "name":"Client", "description":"Represents a OracleDB client.\n", "isDeprecated":false, "isReadOnly":false}], "listeners":[], "functions":[]}]}}}}